{
  "project_info": {
    "project_number": "480149466202",
    "project_id": "todoapp-4901f",
    "storage_bucket": "todoapp-4901f.appspot.com"
  },
  "client": [
    {
      "client_info": {
        "mobilesdk_app_id": "1:480149466202:android:134793e16c2e4fcb667c63",
        "android_client_info": {
          "package_name": "com.example.todo_app"
        }
      },
      "oauth_client": [
        {
          "client_id": "480149466202-m5a7h9t29joteo8tpglgbrr7gp1qc6a5.apps.googleusercontent.com",
          "client_type": 3
        }
      ],
      "api_key": [
        {
          "current_key": "AIzaSyC10oHNPAuRsAc4inewe4Tknu6CZyWzH7Y"
        }
      ],
      "services": {
        "appinvite_service": {
          "other_platform_oauth_client": [
            {
              "client_id": "480149466202-m5a7h9t29joteo8tpglgbrr7gp1qc6a5.apps.googleusercontent.com",
              "client_type": 3
            }
          ]
        }
      }
    }
  ],
  "configuration_version": "1"
}